cscrsademo/__init__.py
cscrsademo-0.1.1.dist-info/METADATA
cscrsademo-0.1.1.dist-info/WHEEL
cscrsademo-0.1.1.dist-info/top_level.txt
cscrsademo-0.1.1.dist-info/RECORD
