Metadata-Version: 2.1
Name: cscrsademo
Version: 0.1.1
Summary: CSC RSA Demo Toolkit
Home-page: UNKNOWN
License: UNKNOWN
Platform: UNKNOWN
Classifier: Programming Language :: Python :: 3
Classifier: Operating System :: OS Independent
Requires-Python: >=3.6
